talPYot/__init__.py
talPYot/main.py
talPYot-0.1.2.dist-info/LICENSE
talPYot-0.1.2.dist-info/METADATA
talPYot-0.1.2.dist-info/WHEEL
talPYot-0.1.2.dist-info/entry_points.txt
talPYot-0.1.2.dist-info/top_level.txt
talPYot-0.1.2.dist-info/RECORD
