Metadata-Version: 2.2
Name: talPYot
Version: 0.1.2
Summary: Provides davening direction to the Kosel
Author-email: Dror Maor <dror.m.maor@gmail.com>
License: MIT License
Project-URL: Homepage, https://github.com/DrorMaor/talPYot
Project-URL: Bug Tracker, https://github.com/DrorMaor/talPYot/issues
Keywords: davening,Kosel,Kotel,Yerushalayim,Jerusalem
Classifier: Programming Language :: Python :: 3
Classifier: License :: OSI Approved :: MIT License
Classifier: Operating System :: OS Independent
License-File: LICENSE
Requires-Dist: geopy
